odoo10_addon_partner_bank_sort_code-10.0.1.0.0.99.dev4-py3.8-nspkg.pth
odoo/addons/partner_bank_sort_code/README.rst
odoo/addons/partner_bank_sort_code/__init__.py
odoo/addons/partner_bank_sort_code/__manifest__.py
odoo/addons/partner_bank_sort_code/i18n/partner_bank_sort_code.pot
odoo/addons/partner_bank_sort_code/models/__init__.py
odoo/addons/partner_bank_sort_code/models/res_bank.py
odoo/addons/partner_bank_sort_code/readme/CONTRIBUTORS.rst
odoo/addons/partner_bank_sort_code/readme/DESCRIPTION.rst
odoo/addons/partner_bank_sort_code/readme/HISTORY.rst
odoo/addons/partner_bank_sort_code/readme/USAGE.rst
odoo/addons/partner_bank_sort_code/static/description/icon.png
odoo/addons/partner_bank_sort_code/static/description/index.html
odoo/addons/partner_bank_sort_code/tests/__init__.py
odoo/addons/partner_bank_sort_code/tests/test_sort_code.py
odoo/addons/partner_bank_sort_code/views/res_bank.xml
odoo10_addon_partner_bank_sort_code-10.0.1.0.0.99.dev4.dist-info/METADATA
odoo10_addon_partner_bank_sort_code-10.0.1.0.0.99.dev4.dist-info/WHEEL
odoo10_addon_partner_bank_sort_code-10.0.1.0.0.99.dev4.dist-info/namespace_packages.txt
odoo10_addon_partner_bank_sort_code-10.0.1.0.0.99.dev4.dist-info/top_level.txt
odoo10_addon_partner_bank_sort_code-10.0.1.0.0.99.dev4.dist-info/RECORD
